my_aws_utils/__init__.py
my_aws_utils/sns_utils.py
my_aws_utils/sqs_utils.py
my_aws_utils-0.1.0.dist-info/METADATA
my_aws_utils-0.1.0.dist-info/WHEEL
my_aws_utils-0.1.0.dist-info/top_level.txt
my_aws_utils-0.1.0.dist-info/RECORD
